resoto/__init__.py
resoto-2.4.1.dist-info/WHEEL
resoto-2.4.1.dist-info/METADATA
resoto-2.4.1.dist-info/RECORD
